django_pdr/__init__.py
django_pdr/admin.py
django_pdr/apps.py
django_pdr/datasources.py
django_pdr/methods.py
django_pdr/models.py
django_pdr/tests.py
django_pdr/views.py
django_pdr/js/README.MD
django_pdr/js/bind-connection-tables.js
django_pdr/js/get-reflection-template.js
django_pdr/js/list_config.js
django_pdr/js/list_db_tables.js
django_pdr/management/__init__.py
django_pdr/management/commands/__init__.py
django_pdr/management/commands/export.py
django_pdr/management/commands/import.py
django_pdr/management/commands/pdr-reflect.py
django_pdr/migrations/__init__.py
django_pdr/sql/README.MD
django_pdr/sql/get_pk.sql
django_pdr/sql/list_tables.sql
django_pdr/sql/mssql+pymssql/create_event_listener.sql
django_pdr/sql/mssql+pymssql/delete_event_listener.sql
django_pdr/sql/mysql+mysqldb/create_event_listener.sql
django_pdr/sql/mysql+mysqldb/delete_event_listener.sql
django_pdr/sql/postgresql/create_event_listener.sql
django_pdr/sql/postgresql/delete_event_listener.sql
django_pdr/sql/sqlite+pysqlite/create_event_listener.sql
django_pdr/sql/sqlite+pysqlite/delete_event_listener.sql
django_pdr/sql/sqlite+pysqlite/list_tables.sql
django_pdr-1.2.16.dist-info/LICENSE
django_pdr-1.2.16.dist-info/METADATA
django_pdr-1.2.16.dist-info/WHEEL
django_pdr-1.2.16.dist-info/top_level.txt
django_pdr-1.2.16.dist-info/RECORD
