Metadata-Version: 2.1
Name: django-pdr
Version: 1.2.16
Summary: A Django app to create and manage live replications of SQL database tables.
Home-page: https://github.com/meena-erian/pdr
Author: Meena (Menas) Erian
Author-email: hi@menas.pro
License: Apache V2 License
Platform: UNKNOWN
Classifier: Environment :: Web Environment
Classifier: Framework :: Django
Classifier: Framework :: Django :: 3.1
Classifier: Intended Audience :: Developers
Classifier: License :: OSI Approved :: Apache Software License
Classifier: Operating System :: OS Independent
Classifier: Programming Language :: Python
Classifier: Programming Language :: Python :: 3
Classifier: Programming Language :: Python :: 3 :: Only
Classifier: Programming Language :: Python :: 3.6
Classifier: Programming Language :: Python :: 3.7
Classifier: Programming Language :: Python :: 3.8
Classifier: Topic :: Internet :: WWW/HTTP
Classifier: Topic :: Internet :: WWW/HTTP :: Dynamic Content
Requires-Python: >=3.6
License-File: LICENSE
Requires-Dist: Django (>=3.1)
Requires-Dist: django-ace (>=1.0.11)
Requires-Dist: psycopg2 (>=2.8.6)
Requires-Dist: pytz (>=2021.1)
Requires-Dist: SQLAlchemy (==1.4.45)
Requires-Dist: django-pgcrypto (>=2.0.0)
Requires-Dist: mysqlclient (>=2.0.3)
Requires-Dist: pymssql (>=2.1.5)
